{
    "time": {
        "cpu_time_user": "00:00:15.949",
        "cpu_time_system": "00:00:00.320",
        "runtime": "00:00:19.422",
        "cpu_time_iowait": "00:00:00.000"
    },
    "peak_resources": {
        "cpu_percent": 109.4,
        "memory_rss": "240MiB",
        "memory_vms": "375MiB",
        "threads": 2
    },
    "avg_resources": {
        "cpu_percent": 82.93762886597939,
        "memory_rss": "203MiB",
        "memory_vms": "335MiB",
        "threads": 1.9793814432989691
    }
}