{
    "time": {
        "cpu_time_user": "00:00:21.339",
        "cpu_time_system": "00:00:00.620",
        "runtime": "00:00:23.014",
        "cpu_time_iowait": "00:00:00.000"
    },
    "peak_resources": {
        "cpu_percent": 109.5,
        "memory_rss": "925MiB",
        "memory_vms": "934MiB",
        "threads": 1
    },
    "avg_resources": {
        "cpu_percent": 94.56826086956512,
        "memory_rss": "465MiB",
        "memory_vms": "471MiB",
        "threads": 0.9956521739130435
    }
}