{
    "time": {
        "cpu_time_user": "00:00:38.350",
        "cpu_time_system": "00:00:00.420",
        "runtime": "00:00:40.113",
        "cpu_time_iowait": "00:00:00.000"
    },
    "peak_resources": {
        "cpu_percent": 115.3,
        "memory_rss": "196MiB",
        "memory_vms": "199MiB",
        "threads": 1
    },
    "avg_resources": {
        "cpu_percent": 96.17229219143577,
        "memory_rss": "132MiB",
        "memory_vms": "136MiB",
        "threads": 0.9974811083123426
    }
}