{
    "time": {
        "cpu_time_user": "00:00:46.570",
        "cpu_time_system": "00:00:00.970",
        "runtime": "00:00:17.192",
        "cpu_time_iowait": "00:00:00.000"
    },
    "peak_resources": {
        "cpu_percent": 437.3,
        "memory_rss": "936MiB",
        "memory_vms": "1GiB",
        "threads": 13
    },
    "avg_resources": {
        "cpu_percent": 273.13488372093025,
        "memory_rss": "530MiB",
        "memory_vms": "1GiB",
        "threads": 10.133720930232561
    }
}