{
    "time": {
        "cpu_time_user": "00:00:24.449",
        "cpu_time_system": "00:00:00.350",
        "runtime": "00:00:26.522",
        "cpu_time_iowait": "00:00:00.000"
    },
    "peak_resources": {
        "cpu_percent": 109.5,
        "memory_rss": "411MiB",
        "memory_vms": "536MiB",
        "threads": 2
    },
    "avg_resources": {
        "cpu_percent": 92.77396226415094,
        "memory_rss": "342MiB",
        "memory_vms": "466MiB",
        "threads": 1.9849056603773585
    }
}