{
    "time": {
        "cpu_time_user": "00:00:26.129",
        "cpu_time_system": "00:00:00.390",
        "runtime": "00:00:31.202",
        "cpu_time_iowait": "00:00:00.000"
    },
    "peak_resources": {
        "cpu_percent": 112.3,
        "memory_rss": "141MiB",
        "memory_vms": "145MiB",
        "threads": 1
    },
    "avg_resources": {
        "cpu_percent": 84.95526315789468,
        "memory_rss": "120MiB",
        "memory_vms": "123MiB",
        "threads": 0.9967105263157895
    }
}